mathpix
