Metadata-Version: 1.0
Name: python-mathpix
Version: 0.2
Summary: Python Mathpix Api Wrapper
Home-page: https://github.com/fatihsucu/python-mathpix
Author: Fatih Sucu
Author-email: fatihsucu0@gmail.com
License: MIT
Platform: UNKNOWN
